cda_client/__init__.py
cda_client/api/__init__.py
cda_client/api/column_values/__init__.py
cda_client/api/column_values/column_values_endpoint_column_values_column_post.py
cda_client/api/columns/__init__.py
cda_client/api/columns/columns_endpoint_columns_get.py
cda_client/api/data/__init__.py
cda_client/api/data/file_fetch_rows_endpoint_data_file_post.py
cda_client/api/data/subject_fetch_rows_endpoint_data_subject_post.py
cda_client/api/release_metadata/__init__.py
cda_client/api/release_metadata/release_metadata_endpoint_release_metadata_get.py
cda_client/api/summary/__init__.py
cda_client/api/summary/file_summary_endpoint_summary_file_post.py
cda_client/api/summary/subject_summary_endpoint_summary_subject_post.py
cda_client/client.py
cda_client/errors.py
cda_client/models/__init__.py
cda_client/models/client_error.py
cda_client/models/column_response_obj.py
cda_client/models/column_response_obj_result_item_type_0.py
cda_client/models/column_values_response_obj.py
cda_client/models/column_values_response_obj_result_item_type_0.py
cda_client/models/data_request_body.py
cda_client/models/http_validation_error.py
cda_client/models/internal_error.py
cda_client/models/paged_response_obj.py
cda_client/models/paged_response_obj_result_item_type_0.py
cda_client/models/release_metadata_obj.py
cda_client/models/release_metadata_obj_result_item_type_0.py
cda_client/models/summary_request_body.py
cda_client/models/summary_response_obj.py
cda_client/models/summary_response_obj_result_item_type_0.py
cda_client/models/validation_error.py
cda_client/py.typed
cda_client/types.py
cda_client-2.0.1.dist-info/METADATA
cda_client-2.0.1.dist-info/WHEEL
cda_client-2.0.1.dist-info/RECORD
